Chem_I_Calc-0.1.4.data/scripts/run_chemicalc
chemicalc/__init__.py
chemicalc/exception.py
chemicalc/instruments.py
chemicalc/plot.py
chemicalc/reference_spectra.py
chemicalc/s2n.py
chemicalc/utils.py
chemicalc_app/__init__.py
chemicalc_app/app.py
chemicalc_app/callbacks_crlb.py
chemicalc_app/callbacks_inst.py
chemicalc_app/callbacks_ref.py
chemicalc_app/layout.py
chemicalc_app/plot.py
chemicalc_app/server.py
chemicalc_app/utils.py
Chem_I_Calc-0.1.4.dist-info/LICENSE
Chem_I_Calc-0.1.4.dist-info/METADATA
Chem_I_Calc-0.1.4.dist-info/WHEEL
Chem_I_Calc-0.1.4.dist-info/top_level.txt
Chem_I_Calc-0.1.4.dist-info/RECORD
